{
  "chart_name": "Translation Status",
  "chart_type": "Report",
  "creation": "2025-04-27 09:30:00",
  "custom_options": "{\n\t\"type\": \"bar\",\n\t\"axisOptions\": {\n\t\t\"shortenYAxisNumbers\": 1\n\t},\n\t\"tooltipOptions\": {},\n\t\"colors\": [\"#28a745\", \"#dc3545\"]\n}",
  "docstatus": 0,
  "doctype": "Dashboard Chart",
  "dynamic_filters_json": "{}",
  "filters_json": "{}",
  "group_by_type": "Count",
  "idx": 0,
  "is_public": 1,
  "is_standard": 1,
  "modified": "2025-09-05 00:50:10.360387",
  "modified_by": "Administrator",
  "module": "Translation Tools",
  "name": "Translation Status",
  "number_of_groups": 0,
  "owner": "Administrator",
  "report_name": "Translation Status Report",
  "roles": [],
  "show_values_over_chart": 0,
  "time_interval": "Yearly",
  "timeseries": 0,
  "timespan": "Last Month",
  "type": "Bar",
  "use_report_chart": 1,
  "y_axis": []
}
